splunksdk/__init__.py
splunksdk/_version.py
splunksdk/splunk.py
splunksdk/utils/__init__.py
splunksdk/utils/configs.py
splunksdk/utils/kvstore.py
splunksdk/utils/login.py
splunksdk/utils/search.py
splunksdk/utils/splunk_utils.py
splunksdk/utils/statics.py
splunk_sdk928-0.0.2.dist-info/LICENSE
splunk_sdk928-0.0.2.dist-info/METADATA
splunk_sdk928-0.0.2.dist-info/WHEEL
splunk_sdk928-0.0.2.dist-info/top_level.txt
splunk_sdk928-0.0.2.dist-info/RECORD
