Metadata-Version: 2.1
Name: splunk-sdk928
Version: 0.0.2
Summary: A Splunk SDK that expands on Splunklib API provided by Splunk to help orchestrate continual processes
Author-email: Adam Taveras <dev@tavnets.com>
License: GNU GENERAL PUBLIC LICENSE
Classifier: License :: OSI Approved :: MIT License
Classifier: Programming Language :: Python :: Implementation
Classifier: Programming Language :: Python :: 3.8
Classifier: Programming Language :: Python :: 3.9
Classifier: Programming Language :: Python :: 3.10
Requires-Python: <4,>=3.8
License-File: LICENSE
Requires-Dist: splunklib >=1.0.0
Requires-Dist: pytoolkit928 ==0.0.*
Requires-Dist: splunk-sdk >=1.7.4
Requires-Dist: numpy >=1.22.2
Requires-Dist: pandas
Requires-Dist: pycryptodome
Provides-Extra: test
Requires-Dist: pytest-cov ; extra == 'test'
Requires-Dist: pytest ; extra == 'test'
Requires-Dist: pytest-mock ; extra == 'test'
Requires-Dist: unittest2 ; extra == 'test'
Requires-Dist: dataclasses ; extra == 'test'
Requires-Dist: black ; extra == 'test'
Requires-Dist: pylint ; extra == 'test'
Requires-Dist: isort ; extra == 'test'
